<?xml version="1.0"?>
<Container version="1">
  <Name>iperf-speedtest</Name>
  <Repository>jakezp/iperf-speedtest</Repository>
  <Registry>https://registry.hub.docker.com/r/jakezp/iperf-speedtest</Registry>
  <Shell>sh</Shell>
  <Privileged>false</Privileged>
  <Support/>
  <Project/>
  <Overview>iperf-speedtest</Overview>
  <Category/>
  <WebUI>http://[IP]:[PORT:80]/</WebUI>
  <TemplateURL/>
  <Icon>https://icon2.kisspng.com/20180419/zhq/kisspng-bandwidth-speedtest-net-computer-icons-throughput-distinguished-guest-5ad8695b8bfd29.3862389815241321875734.jpg</Icon>
  <ExtraParams/>
  <PostArgs/>
  <CPUset/>
  <DateInstalled>1540458514</DateInstalled>
  <DonateText/>
  <DonateLink/>
  <Description>iperf-speedtest</Description>
  <Networking>
    <Mode>bridge</Mode>
    <Publish/>
  </Networking>
  <Data>
    <Volume>
      <HostDir>/mnt/user/appdata/iperf-speedtest/cron</HostDir>
      <ContainerDir>/var/spool/cron/cronjobs</ContainerDir>
      <Mode>rw</Mode>
    </Volume>
  </Data>
  <Environment/>
  <Labels/>
  <Config Name="cron" Target="/var/spool/cron/cronjobs" Default="/mnt/user/appdata/iperf-speedtest/cron" Mode="rw" Description="Container Path: /var/spool/cron/cronjobs" Type="Path" Display="always" Required="true" Mask="false">/mnt/user/appdata/iperf-speedtest/cron</Config>
</Container>
